LICENSE
README.rst
setup.cfg
setup.py
neuraxle/__init__.py
neuraxle/base.py
neuraxle/data_container.py
neuraxle/pipeline.py
neuraxle/union.py
neuraxle.egg-info/PKG-INFO
neuraxle.egg-info/SOURCES.txt
neuraxle.egg-info/dependency_links.txt
neuraxle.egg-info/requires.txt
neuraxle.egg-info/top_level.txt
neuraxle/distributed/__init__.py
neuraxle/distributed/streaming.py
neuraxle/hyperparams/__init__.py
neuraxle/hyperparams/distributions.py
neuraxle/hyperparams/scipy_distributions.py
neuraxle/hyperparams/space.py
neuraxle/logging/__init__.py
neuraxle/logging/logging.py
neuraxle/logging/warnings.py
neuraxle/metaopt/__init__.py
neuraxle/metaopt/auto_ml.py
neuraxle/metaopt/callbacks.py
neuraxle/metaopt/context.py
neuraxle/metaopt/optimizer.py
neuraxle/metaopt/validation.py
neuraxle/metaopt/data/__init__.py
neuraxle/metaopt/data/aggregates.py
neuraxle/metaopt/data/reporting.py
neuraxle/metaopt/data/vanilla.py
neuraxle/metaopt/hyperopt/__init__.py
neuraxle/metaopt/hyperopt/tpe.py
neuraxle/metaopt/repositories/__init__.py
neuraxle/metaopt/repositories/db.py
neuraxle/metaopt/repositories/json.py
neuraxle/metaopt/repositories/repo.py
neuraxle/rest/__init__.py
neuraxle/rest/flask.py
neuraxle/steps/__init__.py
neuraxle/steps/column_transformer.py
neuraxle/steps/data.py
neuraxle/steps/features.py
neuraxle/steps/flow.py
neuraxle/steps/loop.py
neuraxle/steps/misc.py
neuraxle/steps/numpy.py
neuraxle/steps/output_handlers.py
neuraxle/steps/sklearn.py